Workbook
Name ActiveScenario: Assumptions!$B$23
Name AdjustedCap: Assumptions!$B$6
Name CapLimit: Assumptions!$B$4
Name SprintRaces: Assumptions!$B$8
Name StandardRaces: Assumptions!$B$9
Name TotalRaces: Assumptions!$B$7

Sheet Assumptions
A1: F1 COST CAP FINANCIAL MODEL — McLAREN RACING 2025
A2: Parameter | B2: Value | C2: Notes
A4: FIA Cost Cap Limit | B4: 135000000 | C4: USD, 2025 season
A5: Inflation Adjustment % | B5: 0.03 | C5: Applied to selected flyaway races
A6: Adjusted Cap (with inflation) | B6: =B4*(1+B5) -> 139050000 | C6: Auto-calculated
A7: Number of Races | B7: 24 | C7: 2025 F1 Calendar
A8: Number of Sprint Weekends | B8: 6 | C8: Higher operational cost
A9: Standard Race Weekends | B9: =B7-B8 -> 18 | C9: Auto-calculated
A11: EXCLUDED ITEMS (Outside Cost Cap)
A13: Top 3 Driver Salaries | B13: 75000000 | C13: Estimated — Norris, Piastri + reserve
A14: Engine / Power Unit Supply | B14: 20000000 | C14: Supplied by Mercedes, excluded
A15: Marketing & Promotional | B15: 15000000 | C15: Brand activities outside sporting regs
A16: Historical Contractual Commitments | B16: 5000000 | C16: Legacy contracts pre-cap era
A17: Total Excluded | B17: =SUM(B13:B16) -> 115000000 | C17: Auto-calculated
A21: SCENARIO CONTROLS
A23: Active Scenario | B23: Base Case
A24: Scenario Description | B24: =IF(B23="Base Case","Balanced allocation optimising both development and reliability",IF(B23="Aggressive Development","Heavy R&D investment targeting lap time gains — higher risk",IF(B23="Operations Focus","Prioritises race execution and logistics reliability over development",""))) -> Balanced allocation optimising both development and reliability
A27: DEPARTMENT DEFINITIONS
A29: Dept 1 | B29: Aerodynamic R&D | C29: Wind tunnel, CFD simulation, design
A30: Dept 2 | B30: Manufacturing & Production | C30: Parts fabrication, materials, tooling
A31: Dept 3 | B31: Race Operations & Logistics | C31: Freight, travel, hospitality, crew
A32: Dept 4 | B32: Trackside Engineering | C32: Garage equipment, pit crew, comms
A33: Dept 5 | B33: IT & Simulation Infrastructure | C33: Data systems, simulator, software
A34: Dept 6 | B34: Contingency Reserve | C34: Unplanned costs, damage repair buffer
A37: PER-RACE COST ASSUMPTIONS
A38: Standard Race Weekend Cost | B38: 1800000 | C38: Avg operational cost per standard race
A39: Sprint Race Weekend Cost | B39: 2200000 | C39: Higher due to extra sessions + logistics
A40: European Race Premium | B40: -200000 | C40: Lower freight cost vs flyaway
A41: Flyaway Race Premium | B41: 400000 | C41: Long-haul freight, hotel, visa costs
A45: Model Last Updated: | B45: =TODAY() -> 46104

Sheet Budget Allocator
A1: BUDGET ALLOCATOR — FIA COST CAP 2025
A2: Department | B2: Base Case ($) | C2: Aggressive Dev ($) | D2: Operations Focus ($) | E2: Active Allocation ($) | F2: % of Cap | G2: Headroom ($)
B3: Scenario 1 | C3: Scenario 2 | D3: Scenario 3 | E3: Active
A4: Aerodynamic R&D | B4: 42000000 | C4: 52000000 | D4: 35000000 | E4: =IF(ActiveScenario="Base Case",B4,IF(ActiveScenario="Aggressive Development",C4,IF(ActiveScenario="Operations Focus",D4,B4))) -> 42000000 | F4: =E4/CapLimit -> 0.31111111 | G4: =E4 -> 42000000
A5: Manufacturing & Production | B5: 28000000 | C5: 30000000 | D5: 25000000 | E5: =IF(ActiveScenario="Base Case",B5,IF(ActiveScenario="Aggressive Development",C5,IF(ActiveScenario="Operations Focus",D5,B5))) -> 28000000 | F5: =E5/CapLimit -> 0.20740741 | G5: =E5 -> 28000000
A6: Race Operations & Logistics | B6: 22000000 | C6: 15000000 | D6: 32000000 | E6: =IF(ActiveScenario="Base Case",B6,IF(ActiveScenario="Aggressive Development",C6,IF(ActiveScenario="Operations Focus",D6,B6))) -> 22000000 | F6: =E6/CapLimit -> 0.16296296 | G6: =E6 -> 22000000
A7: Trackside Engineering | B7: 18000000 | C7: 18000000 | D7: 18000000 | E7: =IF(ActiveScenario="Base Case",B7,IF(ActiveScenario="Aggressive Development",C7,IF(ActiveScenario="Operations Focus",D7,B7))) -> 18000000 | F7: =E7/CapLimit -> 0.13333333 | G7: =E7 -> 18000000
A8: IT & Simulation Infrastructure | B8: 12000000 | C8: 12000000 | D8: 12000000 | E8: =IF(ActiveScenario="Base Case",B8,IF(ActiveScenario="Aggressive Development",C8,IF(ActiveScenario="Operations Focus",D8,B8))) -> 12000000 | F8: =E8/CapLimit -> 0.088888889 | G8: =E8 -> 12000000
A9: Contingency Reserve | B9: 8000000 | C9: 3000000 | D9: 8000000 | E9: =IF(ActiveScenario="Base Case",B9,IF(ActiveScenario="Aggressive Development",C9,IF(ActiveScenario="Operations Focus",D9,B9))) -> 8000000 | F9: =E9/CapLimit -> 0.059259259 | G9: =E9 -> 8000000
A11: TOTAL | B11: =SUM(B4:B9) -> 130000000 | C11: =SUM(C4:C9) -> 130000000 | D11: =SUM(D4:D9) -> 130000000 | E11: =SUM(E4:E9) -> 130000000 | F11: =SUM(F4:F9) -> 0.96296296 | G11: =SUM(G4:G9) -> 130000000
A13: CAP STATUS | B13: =IF(E11>CapLimit,"⚠ CAP BREACH — OVER BY $"&TEXT(E11-CapLimit,"#,##0"),"✓ WITHIN CAP — HEADROOM: $"&TEXT(CapLimit-E11,"#,##0")) -> ✓ WITHIN CAP — HEADROOM: $50,00,000
A15: Active Scenario: | B15: =ActiveScenario -> Base Case | C15: =IF(ActiveScenario="","",Assumptions!B24) -> Balanced allocation optimising both development and reliability

Sheet Burn Tracker
A1: RACE-BY-RACE BURN TRACKER — 2025 SEASON
A2: # | B2: Race | C2: Type | D2: Location | E2: Estimated Race Cost ($) | F2: Cumulative Spend ($) | G2: Cap Remaining ($) | H2: Burn Rate Status | I2: Breach Risk
A3: 2025 FORMULA 1 SEASON — 24 RACES
A4: 1 | B4: Australian GP | C4: Standard | D4: Flyaway | E4: =IF(C4="Sprint",Assumptions!$B$39,Assumptions!$B$38)+IF(D4="European",Assumptions!$B$40,Assumptions!$B$41) -> 2200000 | F4: =E4 -> 2200000 | G4: =CapLimit-F4 -> 132800000 | H4: =IF(F4>(CapLimit*(A4/TotalRaces)),"🔴 Burning Fast","🟢 On Track") -> 🟢 On Track | I4: =IF(A4=0,"",IF((F4/A4)*TotalRaces>CapLimit,"⚠ BREACH PROJECTED","✓ SAFE")) -> ✓ SAFE | K4: =CapLimit -> 135000000
A5: 2 | B5: Chinese GP | C5: Sprint | D5: Flyaway | E5: =IF(C5="Sprint",Assumptions!$B$39,Assumptions!$B$38)+IF(D5="European",Assumptions!$B$40,Assumptions!$B$41) -> 2600000 | F5: =F4+E5 -> 4800000 | G5: =CapLimit-F5 -> 130200000 | H5: =IF(F5>(CapLimit*(A5/TotalRaces)),"🔴 Burning Fast","🟢 On Track") -> 🟢 On Track | I5: =IF(A5=0,"",IF((F5/A5)*TotalRaces>CapLimit,"⚠ BREACH PROJECTED","✓ SAFE")) -> ✓ SAFE | K5: =CapLimit -> 135000000
A6: 3 | B6: Japanese GP | C6: Standard | D6: Flyaway | E6: =IF(C6="Sprint",Assumptions!$B$39,Assumptions!$B$38)+IF(D6="European",Assumptions!$B$40,Assumptions!$B$41) -> 2200000 | F6: =F5+E6 -> 7000000 | G6: =CapLimit-F6 -> 128000000 | H6: =IF(F6>(CapLimit*(A6/TotalRaces)),"🔴 Burning Fast","🟢 On Track") -> 🟢 On Track | I6: =IF(A6=0,"",IF((F6/A6)*TotalRaces>CapLimit,"⚠ BREACH PROJECTED","✓ SAFE")) -> ✓ SAFE | K6: =CapLimit -> 135000000
A7: 4 | B7: Bahrain GP | C7: Standard | D7: Flyaway | E7: =IF(C7="Sprint",Assumptions!$B$39,Assumptions!$B$38)+IF(D7="European",Assumptions!$B$40,Assumptions!$B$41) -> 2200000 | F7: =F6+E7 -> 9200000 | G7: =CapLimit-F7 -> 125800000 | H7: =IF(F7>(CapLimit*(A7/TotalRaces)),"🔴 Burning Fast","🟢 On Track") -> 🟢 On Track | I7: =IF(A7=0,"",IF((F7/A7)*TotalRaces>CapLimit,"⚠ BREACH PROJECTED","✓ SAFE")) -> ✓ SAFE | K7: =CapLimit -> 135000000
A8: 5 | B8: Saudi Arabian GP | C8: Standard | D8: Flyaway | E8: =IF(C8="Sprint",Assumptions!$B$39,Assumptions!$B$38)+IF(D8="European",Assumptions!$B$40,Assumptions!$B$41) -> 2200000 | F8: =F7+E8 -> 11400000 | G8: =CapLimit-F8 -> 123600000 | H8: =IF(F8>(CapLimit*(A8/TotalRaces)),"🔴 Burning Fast","🟢 On Track") -> 🟢 On Track | I8: =IF(A8=0,"",IF((F8/A8)*TotalRaces>CapLimit,"⚠ BREACH PROJECTED","✓ SAFE")) -> ✓ SAFE | K8: =CapLimit -> 135000000
A9: 6 | B9: Miami GP | C9: Sprint | D9: Flyaway | E9: =IF(C9="Sprint",Assumptions!$B$39,Assumptions!$B$38)+IF(D9="European",Assumptions!$B$40,Assumptions!$B$41) -> 2600000 | F9: =F8+E9 -> 14000000 | G9: =CapLimit-F9 -> 121000000 | H9: =IF(F9>(CapLimit*(A9/TotalRaces)),"🔴 Burning Fast","🟢 On Track") -> 🟢 On Track | I9: =IF(A9=0,"",IF((F9/A9)*TotalRaces>CapLimit,"⚠ BREACH PROJECTED","✓ SAFE")) -> ✓ SAFE | K9: =CapLimit -> 135000000
A10: 7 | B10: Emilia Romagna GP | C10: Standard | D10: European | E10: =IF(C10="Sprint",Assumptions!$B$39,Assumptions!$B$38)+IF(D10="European",Assumptions!$B$40,Assumptions!$B$41) -> 1600000 | F10: =F9+E10 -> 15600000 | G10: =CapLimit-F10 -> 119400000 | H10: =IF(F10>(CapLimit*(A10/TotalRaces)),"🔴 Burning Fast","🟢 On Track") -> 🟢 On Track | I10: =IF(A10=0,"",IF((F10/A10)*TotalRaces>CapLimit,"⚠ BREACH PROJECTED","✓ SAFE")) -> ✓ SAFE | K10: =CapLimit -> 135000000
A11: 8 | B11: Monaco GP | C11: Standard | D11: European | E11: =IF(C11="Sprint",Assumptions!$B$39,Assumptions!$B$38)+IF(D11="European",Assumptions!$B$40,Assumptions!$B$41) -> 1600000 | F11: =F10+E11 -> 17200000 | G11: =CapLimit-F11 -> 117800000 | H11: =IF(F11>(CapLimit*(A11/TotalRaces)),"🔴 Burning Fast","🟢 On Track") -> 🟢 On Track | I11: =IF(A11=0,"",IF((F11/A11)*TotalRaces>CapLimit,"⚠ BREACH PROJECTED","✓ SAFE")) -> ✓ SAFE | K11: =CapLimit -> 135000000
A12: 9 | B12: Spanish GP | C12: Standard | D12: European | E12: =IF(C12="Sprint",Assumptions!$B$39,Assumptions!$B$38)+IF(D12="European",Assumptions!$B$40,Assumptions!$B$41) -> 1600000 | F12: =F11+E12 -> 18800000 | G12: =CapLimit-F12 -> 116200000 | H12: =IF(F12>(CapLimit*(A12/TotalRaces)),"🔴 Burning Fast","🟢 On Track") -> 🟢 On Track | I12: =IF(A12=0,"",IF((F12/A12)*TotalRaces>CapLimit,"⚠ BREACH PROJECTED","✓ SAFE")) -> ✓ SAFE | K12: =CapLimit -> 135000000
A13: 10 | B13: Canadian GP | C13: Standard | D13: Flyaway | E13: =IF(C13="Sprint",Assumptions!$B$39,Assumptions!$B$38)+IF(D13="European",Assumptions!$B$40,Assumptions!$B$41) -> 2200000 | F13: =F12+E13 -> 21000000 | G13: =CapLimit-F13 -> 114000000 | H13: =IF(F13>(CapLimit*(A13/TotalRaces)),"🔴 Burning Fast","🟢 On Track") -> 🟢 On Track | I13: =IF(A13=0,"",IF((F13/A13)*TotalRaces>CapLimit,"⚠ BREACH PROJECTED","✓ SAFE")) -> ✓ SAFE | K13: =CapLimit -> 135000000
A14: 11 | B14: Austrian GP | C14: Standard | D14: European | E14: =IF(C14="Sprint",Assumptions!$B$39,Assumptions!$B$38)+IF(D14="European",Assumptions!$B$40,Assumptions!$B$41) -> 1600000 | F14: =F13+E14 -> 22600000 | G14: =CapLimit-F14 -> 112400000 | H14: =IF(F14>(CapLimit*(A14/TotalRaces)),"🔴 Burning Fast","🟢 On Track") -> 🟢 On Track | I14: =IF(A14=0,"",IF((F14/A14)*TotalRaces>CapLimit,"⚠ BREACH PROJECTED","✓ SAFE")) -> ✓ SAFE | K14: =CapLimit -> 135000000
A15: 12 | B15: British GP | C15: Standard | D15: European | E15: =IF(C15="Sprint",Assumptions!$B$39,Assumptions!$B$38)+IF(D15="European",Assumptions!$B$40,Assumptions!$B$41) -> 1600000 | F15: =F14+E15 -> 24200000 | G15: =CapLimit-F15 -> 110800000 | H15: =IF(F15>(CapLimit*(A15/TotalRaces)),"🔴 Burning Fast","🟢 On Track") -> 🟢 On Track | I15: =IF(A15=0,"",IF((F15/A15)*TotalRaces>CapLimit,"⚠ BREACH PROJECTED","✓ SAFE")) -> ✓ SAFE | K15: =CapLimit -> 135000000
A16: 13 | B16: Belgian GP | C16: Standard | D16: European | E16: =IF(C16="Sprint",Assumptions!$B$39,Assumptions!$B$38)+IF(D16="European",Assumptions!$B$40,Assumptions!$B$41) -> 1600000 | F16: =F15+E16 -> 25800000 | G16: =CapLimit-F16 -> 109200000 | H16: =IF(F16>(CapLimit*(A16/TotalRaces)),"🔴 Burning Fast","🟢 On Track") -> 🟢 On Track | I16: =IF(A16=0,"",IF((F16/A16)*TotalRaces>CapLimit,"⚠ BREACH PROJECTED","✓ SAFE")) -> ✓ SAFE | K16: =CapLimit -> 135000000
... A27: 24 | B27: Abu Dhabi GP | C27: Standard | D27: Flyaway | E27: =IF(C27="Sprint",Assumptions!$B$39,Assumptions!$B$38)+IF(D27="European",Assumptions!$B$40,Assumptions!$B$41) -> 2200000 | F27: =F26+E27 -> 49400000 | G27: =CapLimit-F27 -> 85600000 | H27: =IF(F27>(CapLimit*(A27/TotalRaces)),"🔴 Burning Fast","🟢 On Track") -> 🟢 On Track | I27: =IF(A27=0,"",IF((F27/A27)*TotalRaces>CapLimit,"⚠ BREACH PROJECTED","✓ SAFE")) -> ✓ SAFE | K27: =CapLimit -> 135000000
A28: TOTAL | E28: =SUM(E4:E27) -> 49400000
A30: Total Estimated Season Spend | B30: =F27 -> 49400000
A31: Cap Limit | B31: =CapLimit -> 135000000
A32: Projected Headroom / (Breach) | B32: =B31-B30 -> 85600000
A33: Average Cost Per Race | B33: =F27/TotalRaces -> 2058333.3
A34: Most Expensive Race | B34: =MAX(E4:E27) -> 2600000
A35: Cheapest Race | B35: =MIN(E4:E27) -> 1600000
A36: Sprint Weekends Total Cost | B36: =SUMIF(C4:C27,"Sprint",E4:E27) -> 13000000
A37: Standard Weekends Total Cost | B37: =SUMIF(C4:C27,"Standard",E4:E27) -> 36400000

Sheet Performance Bridge
A1: PERFORMANCE BRIDGE — SPEND TO OUTPUT ANALYSIS
A2: Links financial allocation to estimated on-track performance outcomes
A4: Department | B4: Active Budget ($) | C4: Performance Metric | D4: Estimated Impact | E4: Impact per $10M | F4: Performance Score
A5: Aerodynamic R&D | B5: ='Budget Allocator'!E4 -> 42000000 | C5: Lap Time Delta (seconds) | D5: -0.35 | E5: -0.08 | F5: =ROUND((B5/CapLimit)*100*1.8,1) -> 56
A6: Manufacturing & Production | B6: ='Budget Allocator'!E5 -> 28000000 | C6: Parts Reliability Score | D6: 87 | E6: 3.2 | F6: =ROUND((B6/CapLimit)*100*2.2,1) -> 45.6
A7: Race Operations & Logistics | B7: ='Budget Allocator'!E6 -> 22000000 | C7: Pit Stop Success Rate (%) | D7: 94 | E7: 2.1 | F7: =ROUND((B7/CapLimit)*100*1.6,1) -> 26.1
A8: Trackside Engineering | B8: ='Budget Allocator'!E7 -> 18000000 | C8: Strategic Execution Score | D8: 82 | E8: 1.8 | F8: =ROUND((B8/CapLimit)*100*1.4,1) -> 18.7
A9: IT & Simulation Infrastructure | B9: ='Budget Allocator'!E8 -> 12000000 | C9: Simulation Accuracy Score | D9: 78 | E9: 2.5 | F9: =ROUND((B9/CapLimit)*100*1.9,1) -> 16.9
A10: Contingency Reserve | B10: ='Budget Allocator'!E9 -> 8000000 | C10: Incident Buffer Coverage | D10: 65 | E10: 4 | F10: =ROUND((B10/CapLimit)*100*0.8,1) -> 4.7
A11: TOTAL / AVERAGE | B11: =SUM(B5:B10) -> 130000000 | F11: =AVERAGE(F5:F10) -> 28
A13: PERFORMANCE RETURN ON CAP SPEND (PROCS) INDEX | B13: =F11 -> 28
A14: Active Scenario | B14: =ActiveScenario -> Base Case
A15: Total Budget Deployed | B15: =B11 -> 130000000
A16: Index Interpretation | B16: =IF(F11>=70,"🟢 Strong — Efficient spend-to-performance conversion",IF(F11>=55,"🟡 Moderate — Room to optimise allocation",IF(F11>=40,"🔴 Weak — Consider rebalancing departments","⚠ Critical — Major reallocation needed"))) -> ⚠ Critical — Major reallocation needed
A19: SENSITIVITY ANALYSIS — AERO R&D SPEND SCENARIOS
A20: Scenario | B20: Aero R&D Budget ($) | C20: Lap Time Delta (s) | D20: Change vs Base | E20: PROCS Impact | F20: Recommendation
A21: Conservative (-$10M) | B21: =B5-10000000 -> 32000000 | C21: =D5-(E5*1) -> -0.27 | D21: =C21-D5 -> 0.08 | E21: =F5*0.85 -> 47.6 | F21: Frees $10M for operations
A22: Base (Current) | B22: =B5 -> 42000000 | C22: =D5 -> -0.35 | D22: 0 | E22: =F5 -> 56 | F22: Current allocation
A23: Moderate (+$10M) | B23: =B5+10000000 -> 52000000 | C23: =D5+(E5*1) -> -0.43 | D23: =C23-D5 -> -0.08 | E23: =F5*1.12 -> 62.72 | F23: +0.08s lap time gain
A24: Aggressive (+$20M) | B24: =B5+20000000 -> 62000000 | C24: =D5+(E5*2) -> -0.51 | D24: =C24-D5 -> -0.16 | E24: =F5*1.22 -> 68.32 | F24: +0.16s but cuts contingency
A25: Maximum (+$30M) | B25: =B5+30000000 -> 72000000 | C25: =D5+(E5*3) -> -0.59 | D25: =C25-D5 -> -0.24 | E25: =F5*1.3 -> 72.8 | F25: High risk, low reserve
A28: CHAMPIONSHIP POINTS PROJECTION
A29: Base Points Projection (season) | B29: =ROUND(F11*4.2,0) -> 118
A30: Aggressive Dev Points Projection | B30: =ROUND(('Scenario Analysis'!C15*4.2),0) -> 121
A31: Operations Focus Points Projection | B31: =ROUND(('Scenario Analysis'!D15*4.2),0) -> 116
A32: McLaren Actual 2024 Points | B32: 666
A33: Scaling factor based on McLaren 2024 actual result (666 pts)

Sheet Benchmarking
A1: COMPETITOR BENCHMARKING — 2024 SEASON DATA
A2: Estimated budget allocations and efficiency metrics across top 5 constructors
A4: Metric | B4: McLaren | C4: Red Bull | D4: Mercedes | E4: Ferrari | F4: Aston Martin | G4: McLaren Rank
A5: ESTIMATED CAP ALLOCATION ($M)
A6: Aerodynamic R&D | B6: ='Budget Allocator'!E4/1000000 -> 42 | C6: 58 | D6: 50 | E6: 55 | F6: 28
A7: Manufacturing & Production | B7: ='Budget Allocator'!E5/1000000 -> 28 | C7: 32 | D7: 30 | E7: 29 | F7: 22
A8: Race Operations & Logistics | B8: ='Budget Allocator'!E6/1000000 -> 22 | C8: 18 | D8: 20 | E8: 19 | F8: 25
A9: Trackside Engineering | B9: ='Budget Allocator'!E7/1000000 -> 18 | C9: 12 | D9: 15 | E9: 14 | F9: 18
A10: IT & Simulation | B10: ='Budget Allocator'!E8/1000000 -> 12 | C10: 10 | D10: 12 | E10: 10 | F10: 8
A11: Contingency Reserve | B11: ='Budget Allocator'!E9/1000000 -> 8 | C11: 5 | D11: 8 | E11: 8 | F11: 9
A12: TOTAL CAP SPEND ($M) | B12: =SUM(B6:B11) -> 130 | C12: =SUM(C6:C11) -> 135 | D12: =SUM(D6:D11) -> 135 | E12: =SUM(E6:E11) -> 135 | F12: =SUM(F6:F11) -> 110
A14: 2024 SEASON PERFORMANCE (ACTUAL)
A15: Constructor Points | B15: 666 | C15: 589 | D15: 468 | E15: 652 | F15: 94
A16: Race Wins | B16: 6 | C16: 8 | D16: 4 | E16: 5 | F16: 0
A17: Podiums | B17: 22 | C17: 26 | D17: 14 | E17: 19 | F17: 2
A18: DNF Count | B18: 8 | C18: 9 | D18: 11 | E18: 10 | F18: 14
A20: EFFICIENCY METRICS (CALCULATED)
A21: Points per $M Spent | B21: =ROUND(B15/B12,1) -> 5.1 | C21: =ROUND(C15/C12,1) -> 4.4 | D21: =ROUND(D15/D12,1) -> 3.5 | E21: =ROUND(E15/E12,1) -> 4.8 | F21: =ROUND(F15/F12,1) -> 0.9 | G21: =RANK(B21,B21:F21,0) -> 1
A22: Wins per $10M Spent | B22: =ROUND(B16/(B12/10),2) -> 0.46 | C22: =ROUND(C16/(C12/10),2) -> 0.59 | D22: =ROUND(D16/(D12/10),2) -> 0.3 | E22: =ROUND(E16/(E12/10),2) -> 0.37 | F22: =ROUND(F16/(F12/10),2) -> 0 | G22: =RANK(B22,B22:F22,0) -> 2
A23: Reliability Score | B23: =ROUND(100-(B18/24*100),1) -> 66.7 | C23: =ROUND(100-(C18/24*100),1) -> 62.5 | D23: =ROUND(100-(D18/24*100),1) -> 54.2 | E23: =ROUND(100-(E18/24*100),1) -> 58.3 | F23: =ROUND(100-(F18/24*100),1) -> 41.7 | G23: =RANK(B23,B23:F23,0) -> 1
A24: Aero Investment Ratio (%) | B24: =ROUND(B6/B12*100,1) -> 32.3 | C24: =ROUND(C6/C12*100,1) -> 43 | D24: =ROUND(D6/D12*100,1) -> 37 | E24: =ROUND(E6/E12*100,1) -> 40.7 | F24: =ROUND(F6/F12*100,1) -> 25.5 | G24: =IF(B24>AVERAGE(C24:F24),"Above avg","Below avg") -> Below avg
A26: McLaren Strategic Position | B26: =IF(AVERAGE(G21:G24)<=2,"🟢 Top Tier — Leading on efficiency metrics",IF(AVERAGE(G21:G24)<=3,"🟡 Competitive — Mid-pack efficiency",IF(AVERAGE(G21:G24)<=4,"🔴 Trailing — Efficiency gaps vs top teams","⚠ Significant gap — Strategic reallocation needed"))) -> 🟢 Top Tier — Leading on efficiency metrics
A28: STRATEGIC GAP ANALYSIS — McLAREN vs TOP 2
A29: Department | B29: McLaren ($M) | C29: Top 2 Average ($M) | D29: Gap ($M) | E29: Gap (%) | F29: Implication
A30: Aerodynamic R&D | B30: =B6 -> 42 | C30: =AVERAGE(C6,E6) -> 56.5 | D30: =B30-C30 -> -14.5 | E30: =ROUND(D30/C30*100,1) -> -25.7 | F30: Underspending vs rivals — lap time risk
A31: Manufacturing & Production | B31: =B7 -> 28 | C31: =AVERAGE(C7,E7) -> 30.5 | D31: =B31-C31 -> -2.5 | E31: =ROUND(D31/C31*100,1) -> -8.2 | F31: Broadly aligned with top 2
A32: Race Operations & Logistics | B32: =B8 -> 22 | C32: =AVERAGE(C8,E8) -> 18.5 | D32: =B32-C32 -> 3.5 | E32: =ROUND(D32/C32*100,1) -> 18.9 | F32: Overspending — strong operational focus
A33: Trackside Engineering | B33: =B9 -> 18 | C33: =AVERAGE(C9,E9) -> 13 | D33: =B33-C33 -> 5 | E33: =ROUND(D33/C33*100,1) -> 38.5 | F33: Aligned — no significant gap
A34: IT & Simulation | B34: =B10 -> 12 | C34: =AVERAGE(C10,E10) -> 10 | D34: =B34-C34 -> 2 | E34: =ROUND(D34/C34*100,1) -> 20 | F34: Underspending — simulation risk
A35: Contingency Reserve | B35: =B11 -> 8 | C35: =AVERAGE(C11,E11) -> 6.5 | D35: =B35-C35 -> 1.5 | E35: =ROUND(D35/C35*100,1) -> 23.1 | F35: Underspending — lower incident buffer
A38: Data Sources: | B38: Constructor points & results: Formula1.com official 2024 standings. Budget estimates: Motorsport Week, Forbes F1 team value reports, RaceFans financial analysis. McLaren allocation pulls live from Budget Allocator sheet.

Sheet Scenario Analysis
A1: SCENARIO ANALYSIS — THREE-WAY COMPARISON
A2: Side-by-side comparison of all three budget scenarios and their projected outcomes
A4: METRIC | B4: BASE CASE | C4: AGGRESSIVE DEV | D4: OPERATIONS FOCUS | E4: INSIGHT
A5: BUDGET ALLOCATION SUMMARY ($M)
A6: Aerodynamic R&D | B6: ='Budget Allocator'!B4/1000000 -> 42 | C6: ='Budget Allocator'!C4/1000000 -> 52 | D6: ='Budget Allocator'!D4/1000000 -> 35 | E6: Red Bull spend ~$58M — McLaren trails in aero
A7: Manufacturing & Production | B7: ='Budget Allocator'!B5/1000000 -> 28 | C7: ='Budget Allocator'!C5/1000000 -> 30 | D7: ='Budget Allocator'!D5/1000000 -> 25 | E7: All 3 scenarios broadly aligned here
A8: Race Operations & Logistics | B8: ='Budget Allocator'!B6/1000000 -> 22 | C8: ='Budget Allocator'!C6/1000000 -> 15 | D8: ='Budget Allocator'!D6/1000000 -> 32 | E8: Ops Focus commits 2x vs Aggressive Dev
A9: Trackside Engineering | B9: ='Budget Allocator'!B7/1000000 -> 18 | C9: ='Budget Allocator'!C7/1000000 -> 18 | D9: ='Budget Allocator'!D7/1000000 -> 18 | E9: Consistent across all 3 — stable priority
A10: IT & Simulation Infrastructure | B10: ='Budget Allocator'!B8/1000000 -> 12 | C10: ='Budget Allocator'!C8/1000000 -> 12 | D10: ='Budget Allocator'!D8/1000000 -> 12 | E10: Minor variation — not a key lever
A11: Contingency Reserve | B11: ='Budget Allocator'!B9/1000000 -> 8 | C11: ='Budget Allocator'!C9/1000000 -> 3 | D11: ='Budget Allocator'!D9/1000000 -> 8 | E11: Aggressive Dev cuts reserve to just $3M
A12: TOTAL | B12: =SUM(B6:B11) -> 130 | C12: =SUM(C6:C11) -> 130 | D12: =SUM(D6:D11) -> 130 | E12: All scenarios within $135M cap ✓
A14: PERFORMANCE PROJECTIONS
A15: PROCS Performance Index | B15: ='Performance Bridge'!F11 -> 28 | C15: =ROUND(AVERAGE('Budget Allocator'!C4/CapLimit*100*1.8,'Budget Allocator'!C5/CapLimit*100*2.2,'Budget Allocator'!C6/CapLimit*100*1.6,'Budget Allocator'!C7/CapLimit*100*1.4,'Budget Allocator'!C8/CapLimit*100*1.9,'Budget Allocator'!C9/CapLimit*100*0.8),1) -> 28.9 | D15: =ROUND(AVERAGE('Budget Allocator'!D4/CapLimit*100*1.8,'Budget Allocator'!D5/CapLimit*100*2.2,'Budget Allocator'!D6/CapLimit*100*1.6,'Budget Allocator'!D7/CapLimit*100*1.4,'Budget Allocator'!D8/CapLimit*100*1.9,'Budget Allocator'!D9/CapLimit*100*0.8),1) -> 27.6 | E15: Higher PROCS = better spend efficiency
A16: Projected Championship Points | B16: =ROUND(B15*4.2,0) -> 118 | C16: =ROUND(C15*4.2,0) -> 121 | D16: =ROUND(D15*4.2,0) -> 116 | E16: Based on McLaren 2024 scaling factor
A17: Aero Lap Time Advantage (s) | B17: -0.35 | C17: =ROUND(-0.35+(('Budget Allocator'!C4-'Budget Allocator'!B4)/10000000*-0.08),2) -> -0.43 | D17: =ROUND(-0.35+(('Budget Allocator'!D4-'Budget Allocator'!B4)/10000000*-0.08),2) -> -0.29 | E17: Aggressive Dev buys ~0.08s extra pace
A18: Contingency Reserve ($M) | B18: ='Budget Allocator'!B9/1000000 -> 8 | C18: ='Budget Allocator'!C9/1000000 -> 3 | D18: ='Budget Allocator'!D9/1000000 -> 8 | E18: Aggressive Dev reserve critically low
A20: RISK ASSESSMENT
A21: Development Risk | B21: Low | C21: High | D21: Low | E21: Aero investment drives uncertainty
A22: Operational Risk | B22: Low | C22: High | D22: Very Low | E22: Low ops budget = logistics vulnerability
A23: Reliability Risk | B23: Low | C23: Medium | D23: Low | E23: Contingency buffer drives this
A24: Strategic Flexibility | B24: High | C24: Low | D24: Medium | E24: Reserve headroom = flexibility
A25: Recommended For | B25: Balanced season | C25: Title push attempt | D25: Street/wet circuits | E25: Context dependent
A27: SCENARIO RECOMMENDATION
A28: Recommended Scenario: | B28: =IF(AND(B15>=C15,B15>=D15),"Base Case",IF(AND(C15>=B15,C15>=D15),"Aggressive Development","Operations Focus")) -> Aggressive Development
A29: Rationale: | B29: Base Case offers the strongest balance between performance investment and risk management. Aggressive Development maximises lap time potential but sacrifices contingency reserve to critically low levels ($3M). Operations Focus prioritises reliability — best suited for a mid-season recovery strategy.
A30: Active Scenario vs Recommendation: | B30: =IF(ActiveScenario=B28,"✓ Currently running recommended scenario","⚠ Consider switching to "&B28) -> ⚠ Consider switching to Aggressive Development

Sheet Dashboard
A1: F1 COST CAP FINANCIAL MODEL — McLAREN RACING 2025
A2: Strategic Financial Analysis | FIA Cost Cap Compliance | Performance Benchmarking
A3: Active Scenario: | I3: =ActiveScenario -> Base Case
A4: Scenario Description: | I4: =Assumptions!B24 -> Balanced allocation optimising both development and reliability
L5: ="Last Updated: "&TEXT(TODAY(),"DD-MMM-YYYY") -> Last Updated: 23-Mar-2026
A6: TOTAL CAP ALLOCATED | D6: CAP STATUS | G6: PROCS PERFORMANCE INDEX | J6: PROJECTED CHAMPIONSHIP PTS
A7: ='Budget Allocator'!E11 -> 130000000 | D7: ='Budget Allocator'!B13 -> ✓ WITHIN CAP — HEADROOM: $50,00,000 | G7: ='Performance Bridge'!B13 -> 28 | J7: ='Performance Bridge'!B29 -> 118
A10: ="of $135M cap ("&TEXT('Budget Allocator'!F11,"0.0%")&" deployed)" -> of $135M cap (96.3% deployed) | D10: ="Headroom: $"&TEXT(CapLimit-'Budget Allocator'!E11,"#,##0") -> Headroom: $50,00,000 | G10: ='Performance Bridge'!B16 -> ⚠ Critical — Major reallocation needed | J10: ="McLaren 2024 actual: 666 pts" -> McLaren 2024 actual: 666 pts
A11: BUDGET ALLOCATION | D11: SEASON BURN OVERVIEW | I11: COMPETITOR BENCHMARKING
A12: Department | B12: Budget ($M) | C12: % of Cap | D12: Score | E12: 2025 SEASON OPERATIONAL COSTS | I12: EFFICIENCY VS RIVALS
A13: ='Budget Allocator'!A4 -> Aerodynamic R&D | B13: ='Budget Allocator'!E4/1000000 -> 42 | C13: ='Budget Allocator'!F4 -> 0.31111111 | D13: ='Performance Bridge'!F5 -> 56 | E13: Total Season Est. Spend | G13: ='Burn Tracker'!B30 -> 49400000 | J13: McLAREN | K13: BEST RIVAL | L13: McLAREN RANK
A14: ='Budget Allocator'!A5 -> Manufacturing & Production | B14: ='Budget Allocator'!E5/1000000 -> 28 | C14: ='Budget Allocator'!F5 -> 0.20740741 | D14: ='Performance Bridge'!F6 -> 45.6 | E14: Average Cost Per Race | G14: ='Burn Tracker'!B33 -> 2058333.3 | I14: Points per $M | J14: =Benchmarking!B21 -> 5.1 | K14: =MAX(Benchmarking!C21:F21) -> 4.8 | L14: =Benchmarking!G21 -> 1
A15: ='Budget Allocator'!A6 -> Race Operations & Logistics | B15: ='Budget Allocator'!E6/1000000 -> 22 | C15: ='Budget Allocator'!F6 -> 0.16296296 | D15: ='Performance Bridge'!F7 -> 26.1 | E15: Most Expensive Race | G15: ='Burn Tracker'!B34 -> 2600000 | I15: Wins per $10M | J15: =Benchmarking!B22 -> 0.46 | K15: =MAX(Benchmarking!C22:F22) -> 0.59 | L15: =Benchmarking!G22 -> 2
A16: ='Budget Allocator'!A7 -> Trackside Engineering | B16: ='Budget Allocator'!E7/1000000 -> 18 | C16: ='Budget Allocator'!F7 -> 0.13333333 | D16: ='Performance Bridge'!F8 -> 18.7 | E16: Cheapest Race | G16: ='Burn Tracker'!B35 -> 1600000 | I16: Reliability Score | J16: =Benchmarking!B23 -> 66.7 | K16: =MAX(Benchmarking!C23:F23) -> 62.5 | L16: =Benchmarking!G23 -> 1
A17: ='Budget Allocator'!A8 -> IT & Simulation Infrastructure | B17: ='Budget Allocator'!E8/1000000 -> 12 | C17: ='Budget Allocator'!F8 -> 0.088888889 | D17: ='Performance Bridge'!F9 -> 16.9 | E17: Sprint Weekends Cost | G17: ='Burn Tracker'!B36 -> 13000000 | I17: STRATEGIC POSITION
A18: ='Budget Allocator'!A9 -> Contingency Reserve | B18: ='Budget Allocator'!E9/1000000 -> 8 | C18: ='Budget Allocator'!F9 -> 0.059259259 | D18: ='Performance Bridge'!F10 -> 4.7 | E18: Standard Weekends Cost | G18: ='Burn Tracker'!B37 -> 36400000 | I18: =Benchmarking!B26 -> 🟢 Top Tier — Leading on efficiency metrics
A19: TOTAL | B19: ='Budget Allocator'!E11/1000000 -> 130 | C19: ='Budget Allocator'!F11 -> 0.96296296 | D19: =AVERAGE('Performance Bridge'!F5:F10) -> 28 | E19: Projected Headroom | G19: ='Burn Tracker'!B32 -> 85600000
I20: STRATEGIC GAP vs TOP 2
E21: BURN RATE SUMMARY | I21: Aero R&D | J21: =Benchmarking!D30 -> -14.5 | K21: =IF(Benchmarking!D30<0,"Underspend ⚠","Overspend") -> Underspend ⚠
E22: Cap Limit | G22: =CapLimit -> 135000000 | I22: Race Operations | J22: =Benchmarking!D32 -> 3.5 | K22: =IF(Benchmarking!D32<0,"Underspend ⚠","Overspend") -> Overspend
E23: Remaining After Ops | G23: =CapLimit-'Burn Tracker'!B30 -> 85600000 | I23: IT & Simulation | J23: =Benchmarking!D34 -> 2 | K23: =IF(Benchmarking!D34<0,"Underspend ⚠","Overspend") -> Overspend
E24: Ops as % of Cap | G24: =ROUND('Burn Tracker'!B30/CapLimit*100,1)&"%" -> 36.6%
A26: EXECUTIVE SUMMARY
A27: ="Under the "&ActiveScenario&" scenario, McLaren deploys $"&TEXT('Budget Allocator'!E11/1000000,"0.0")&"M of the $135M FIA cost cap across 6 departments. The PROCS efficiency index stands at "&TEXT('Performance Bridge'!B13,"0.0")&", projecting "&TEXT('Performance Bridge'!B29,"0")&" championship points based on 2024 performance scaling. Season operational spend is estimated at $"&TEXT('Burn Tracker'!B30/1000000,"0.0")&"M across 24 races. "&Benchmarking!B26&"." -> Under the Base Case scenario, McLaren deploys $130.0M of the $135M FIA cost cap across 6 departments. The PROCS efficiency index stands at 28.0, projecting 118 championship points based on 2024 performance scaling. Season operational spend is estimated at $49.4M across 24 races. 🟢 Top Tier — Leading on efficiency metrics.
